{
  "_meta": {
    "records": 62,
    "skipped_missing_venue": 5,
    "skipped_missing_capacity": 23
  },
  "matches": [
    {
      "fixture_id": 1223975,
      "date": "2024-08-23T18:30:00+00:00",
      "venue_id": 20471,
      "venue_name": "BORUSSIA-PARK",
      "city": "Mönchengladbach",
      "capacity": 54057,
      "match": "Borussia Mönchengladbach vs Bayer Leverkusen",
      "yellow_home": 1,
      "red_home": 0,
      "yellow_away": 0,
      "red_away": 0,
      "yellow_total": 1,
      "red_total": 0,
      "cards_total": 1
    },
    {
      "fixture_id": 1223979,
      "date": "2024-08-24T13:30:00+00:00",
      "venue_id": 12717,
      "venue_name": "Europa-Park Stadion",
      "city": "Freiburg im Breisgau",
      "capacity": 34700,
      "match": "SC Freiburg vs VfB Stuttgart",
      "yellow_home": 2,
      "red_home": 0,
      "yellow_away": 1,
      "red_away": 0,
      "yellow_total": 3,
      "red_total": 0,
      "cards_total": 3
    },
    {
      "fixture_id": 1223982,
      "date": "2024-08-24T13:30:00+00:00",
      "venue_id": 11899,
      "venue_name": "MEWA ARENA",
      "city": "Mainz",
      "capacity": 34034,
      "match": "FSV Mainz 05 vs Union Berlin",
      "yellow_home": 1,
      "red_home": 0,
      "yellow_away": 3,
      "red_away": 0,
      "yellow_total": 4,
      "red_total": 0,
      "cards_total": 4
    },
    {
      "fixture_id": 1223978,
      "date": "2024-08-24T13:30:00+00:00",
      "venue_id": 724,
      "venue_name": "PreZero Arena",
      "city": "Sinsheim",
      "capacity": 30164,
      "match": "1899 Hoffenheim vs Holstein Kiel",
      "yellow_home": 2,
      "red_home": 0,
      "yellow_away": 3,
      "red_away": 1,
      "yellow_total": 5,
      "red_total": 1,
      "cards_total": 6
    },
    {
      "fixture_id": 1223980,
      "date": "2024-08-24T13:30:00+00:00",
      "venue_id": 698,
      "venue_name": "WWK Arena",
      "city": "Augsburg",
      "capacity": 30662,
      "match": "FC Augsburg vs Werder Bremen",
      "yellow_home": 3,
      "red_home": 0,
      "yellow_away": 1,
      "red_away": 0,
      "yellow_total": 4,
      "red_total": 0,
      "cards_total": 4
    },
    {
      "fixture_id": 1223981,
      "date": "2024-08-25T13:30:00+00:00",
      "venue_id": 752,
      "venue_name": "Volkswagen Arena",
      "city": "Wolfsburg",
      "capacity": 30000,
      "match": "VfL Wolfsburg vs Bayern München",
      "yellow_home": 2,
      "red_home": 0,
      "yellow_away": 3,
      "red_away": 0,
      "yellow_total": 5,
      "red_total": 0,
      "cards_total": 5
    },
    {
      "fixture_id": 1223983,
      "date": "2024-08-25T15:30:00+00:00",
      "venue_id": 745,
      "venue_name": "Millerntor-Stadion",
      "city": "Hamburg",
      "capacity": 29564,
      "match": "FC St. Pauli vs 1. FC Heidenheim",
      "yellow_home": 2,
      "red_home": 0,
      "yellow_away": 3,
      "red_away": 0,
      "yellow_total": 5,
      "red_total": 0,
      "cards_total": 5
    },
    {
      "fixture_id": 1223990,
      "date": "2024-08-30T18:30:00+00:00",
      "venue_id": 748,
      "venue_name": "Stadion An der Alten Försterei",
      "city": "Berlin",
      "capacity": 22467,
      "match": "Union Berlin vs FC St. Pauli",
      "yellow_home": 3,
      "red_home": 0,
      "yellow_away": 1,
      "red_away": 0,
      "yellow_total": 4,
      "red_total": 0,
      "cards_total": 4
    },
    {
      "fixture_id": 1223991,
      "date": "2024-08-31T13:30:00+00:00",
      "venue_id": 751,
      "venue_name": "Vonovia Ruhrstadion",
      "city": "Bochum",
      "capacity": 27599,
      "match": "VfL Bochum vs Borussia Mönchengladbach",
      "yellow_home": 1,
      "red_home": 0,
      "yellow_away": 0,
      "red_away": 0,
      "yellow_total": 1,
      "red_total": 0,
      "cards_total": 1
    },
    {
      "fixture_id": 1223992,
      "date": "2024-08-31T13:30:00+00:00",
      "venue_id": 725,
      "venue_name": "Holstein-Stadion",
      "city": "Kiel",
      "capacity": 15034,
      "match": "Holstein Kiel vs VfL Wolfsburg",
      "yellow_home": 4,
      "red_home": 0,
      "yellow_away": 7,
      "red_away": 0,
      "yellow_total": 11,
      "red_total": 0,
      "cards_total": 11
    },
    {
      "fixture_id": 1223984,
      "date": "2024-08-31T16:30:00+00:00",
      "venue_id": 699,
      "venue_name": "BayArena",
      "city": "Leverkusen",
      "capacity": 30210,
      "match": "Bayer Leverkusen vs RB Leipzig",
      "yellow_home": 3,
      "red_home": 0,
      "yellow_away": 1,
      "red_away": 0,
      "yellow_total": 4,
      "red_total": 0,
      "cards_total": 4
    },
    {
      "fixture_id": 1223988,
      "date": "2024-09-01T13:30:00+00:00",
      "venue_id": 723,
      "venue_name": "Voith-Arena",
      "city": "Heidenheim an der Brenz",
      "capacity": 15000,
      "match": "1. FC Heidenheim vs FC Augsburg",
      "yellow_home": 1,
      "red_home": 0,
      "yellow_away": 4,
      "red_away": 0,
      "yellow_total": 5,
      "red_total": 0,
      "cards_total": 5
    },
    {
      "fixture_id": 1223996,
      "date": "2024-09-14T13:30:00+00:00",
      "venue_id": 12717,
      "venue_name": "Europa-Park Stadion",
      "city": "Freiburg im Breisgau",
      "capacity": 34700,
      "match": "SC Freiburg vs VfL Bochum",
      "yellow_home": 0,
      "red_home": 0,
      "yellow_away": 3,
      "red_away": 0,
      "yellow_total": 3,
      "red_total": 0,
      "cards_total": 3
    },
    {
      "fixture_id": 1223998,
      "date": "2024-09-14T13:30:00+00:00",
      "venue_id": 752,
      "venue_name": "Volkswagen Arena",
      "city": "Wolfsburg",
      "capacity": 30000,
      "match": "VfL Wolfsburg vs Eintracht Frankfurt",
      "yellow_home": 1,
      "red_home": 0,
      "yellow_away": 2,
      "red_away": 0,
      "yellow_total": 3,
      "red_total": 0,
      "cards_total": 3
    },
    {
      "fixture_id": 1224000,
      "date": "2024-09-14T13:30:00+00:00",
      "venue_id": 20471,
      "venue_name": "BORUSSIA-PARK",
      "city": "Mönchengladbach",
      "capacity": 54057,
      "match": "Borussia Mönchengladbach vs VfB Stuttgart",
      "yellow_home": 2,
      "red_home": 0,
      "yellow_away": 2,
      "red_away": 0,
      "yellow_total": 4,
      "red_total": 0,
      "cards_total": 4
    },
    {
      "fixture_id": 1223995,
      "date": "2024-09-14T13:30:00+00:00",
      "venue_id": 724,
      "venue_name": "PreZero Arena",
      "city": "Sinsheim",
      "capacity": 30164,
      "match": "1899 Hoffenheim vs Bayer Leverkusen",
      "yellow_home": 2,
      "red_home": 0,
      "yellow_away": 2,
      "red_away": 0,
      "yellow_total": 4,
      "red_total": 0,
      "cards_total": 4
    },
    {
      "fixture_id": 1224001,
      "date": "2024-09-14T16:30:00+00:00",
      "venue_id": 725,
      "venue_name": "Holstein-Stadion",
      "city": "Kiel",
      "capacity": 15034,
      "match": "Holstein Kiel vs Bayern München",
      "yellow_home": 0,
      "red_home": 0,
      "yellow_away": 1,
      "red_away": 0,
      "yellow_total": 1,
      "red_total": 0,
      "cards_total": 1
    },
    {
      "fixture_id": 1223997,
      "date": "2024-09-15T13:30:00+00:00",
      "venue_id": 698,
      "venue_name": "WWK Arena",
      "city": "Augsburg",
      "capacity": 30662,
      "match": "FC Augsburg vs FC St. Pauli",
      "yellow_home": 4,
      "red_home": 0,
      "yellow_away": 3,
      "red_away": 0,
      "yellow_total": 7,
      "red_total": 0,
      "cards_total": 7
    },
    {
      "fixture_id": 1223999,
      "date": "2024-09-15T15:30:00+00:00",
      "venue_id": 11899,
      "venue_name": "MEWA ARENA",
      "city": "Mainz",
      "capacity": 34034,
      "match": "FSV Mainz 05 vs Werder Bremen",
      "yellow_home": 3,
      "red_home": 0,
      "yellow_away": 1,
      "red_away": 1,
      "yellow_total": 4,
      "red_total": 1,
      "cards_total": 5
    },
    {
      "fixture_id": 1224007,
      "date": "2024-09-20T18:30:00+00:00",
      "venue_id": 698,
      "venue_name": "WWK Arena",
      "city": "Augsburg",
      "capacity": 30662,
      "match": "FC Augsburg vs FSV Mainz 05",
      "yellow_home": 3,
      "red_home": 1,
      "yellow_away": 5,
      "red_away": 1,
      "yellow_total": 8,
      "red_total": 2,
      "cards_total": 10
    },
    {
      "fixture_id": 1224009,
      "date": "2024-09-21T13:30:00+00:00",
      "venue_id": 751,
      "venue_name": "Vonovia Ruhrstadion",
      "city": "Bochum",
      "capacity": 27599,
      "match": "VfL Bochum vs Holstein Kiel",
      "yellow_home": 4,
      "red_home": 0,
      "yellow_away": 1,
      "red_away": 0,
      "yellow_total": 5,
      "red_total": 0,
      "cards_total": 5
    },
    {
      "fixture_id": 1224005,
      "date": "2024-09-21T13:30:00+00:00",
      "venue_id": 723,
      "venue_name": "Voith-Arena",
      "city": "Heidenheim an der Brenz",
      "capacity": 15000,
      "match": "1. FC Heidenheim vs SC Freiburg",
      "yellow_home": 1,
      "red_home": 0,
      "yellow_away": 1,
      "red_away": 0,
      "yellow_total": 2,
      "red_total": 0,
      "cards_total": 2
    },
    {
      "fixture_id": 1224008,
      "date": "2024-09-21T13:30:00+00:00",
      "venue_id": 748,
      "venue_name": "Stadion An der Alten Försterei",
      "city": "Berlin",
      "capacity": 22467,
      "match": "Union Berlin vs 1899 Hoffenheim",
      "yellow_home": 3,
      "red_home": 0,
      "yellow_away": 3,
      "red_away": 0,
      "yellow_total": 6,
      "red_total": 0,
      "cards_total": 6
    },
    {
      "fixture_id": 1224002,
      "date": "2024-09-22T13:30:00+00:00",
      "venue_id": 699,
      "venue_name": "BayArena",
      "city": "Leverkusen",
      "capacity": 30210,
      "match": "Bayer Leverkusen vs VfL Wolfsburg",
      "yellow_home": 4,
      "red_home": 0,
      "yellow_away": 5,
      "red_away": 1,
      "yellow_total": 9,
      "red_total": 1,
      "cards_total": 10
    },
    {
      "fixture_id": 1224010,
      "date": "2024-09-22T17:30:00+00:00",
      "venue_id": 745,
      "venue_name": "Millerntor-Stadion",
      "city": "Hamburg",
      "capacity": 29564,
      "match": "FC St. Pauli vs RB Leipzig",
      "yellow_home": 2,
      "red_home": 0,
      "yellow_away": 1,
      "red_away": 0,
      "yellow_total": 3,
      "red_total": 0,
      "cards_total": 3
    },
    {
      "fixture_id": 1224015,
      "date": "2024-09-28T13:30:00+00:00",
      "venue_id": 12717,
      "venue_name": "Europa-Park Stadion",
      "city": "Freiburg im Breisgau",
      "capacity": 34700,
      "match": "SC Freiburg vs FC St. Pauli",
      "yellow_home": 3,
      "red_home": 0,
      "yellow_away": 3,
      "red_away": 0,
      "yellow_total": 6,
      "red_total": 0,
      "cards_total": 6
    },
    {
      "fixture_id": 1224016,
      "date": "2024-09-28T13:30:00+00:00",
      "venue_id": 752,
      "venue_name": "Volkswagen Arena",
      "city": "Wolfsburg",
      "capacity": 30000,
      "match": "VfL Wolfsburg vs VfB Stuttgart",
      "yellow_home": 5,
      "red_home": 0,
      "yellow_away": 2,
      "red_away": 1,
      "yellow_total": 7,
      "red_total": 1,
      "cards_total": 8
    },
    {
      "fixture_id": 1224018,
      "date": "2024-09-28T13:30:00+00:00",
      "venue_id": 20471,
      "venue_name": "BORUSSIA-PARK",
      "city": "Mönchengladbach",
      "capacity": 54057,
      "match": "Borussia Mönchengladbach vs Union Berlin",
      "yellow_home": 3,
      "red_home": 0,
      "yellow_away": 1,
      "red_away": 0,
      "yellow_total": 4,
      "red_total": 0,
      "cards_total": 4
    },
    {
      "fixture_id": 1224017,
      "date": "2024-09-28T13:30:00+00:00",
      "venue_id": 11899,
      "venue_name": "MEWA ARENA",
      "city": "Mainz",
      "capacity": 34034,
      "match": "FSV Mainz 05 vs 1. FC Heidenheim",
      "yellow_home": 4,
      "red_home": 1,
      "yellow_away": 4,
      "red_away": 1,
      "yellow_total": 8,
      "red_total": 2,
      "cards_total": 10
    },
    {
      "fixture_id": 1224019,
      "date": "2024-09-29T13:30:00+00:00",
      "venue_id": 725,
      "venue_name": "Holstein-Stadion",
      "city": "Kiel",
      "capacity": 15034,
      "match": "Holstein Kiel vs Eintracht Frankfurt",
      "yellow_home": 1,
      "red_home": 0,
      "yellow_away": 3,
      "red_away": 0,
      "yellow_total": 4,
      "red_total": 0,
      "cards_total": 4
    },
    {
      "fixture_id": 1224014,
      "date": "2024-09-29T15:30:00+00:00",
      "venue_id": 724,
      "venue_name": "PreZero Arena",
      "city": "Sinsheim",
      "capacity": 30164,
      "match": "1899 Hoffenheim vs Werder Bremen",
      "yellow_home": 3,
      "red_home": 1,
      "yellow_away": 3,
      "red_away": 0,
      "yellow_total": 6,
      "red_total": 1,
      "cards_total": 7
    },
    {
      "fixture_id": 1224025,
      "date": "2024-10-04T18:30:00+00:00",
      "venue_id": 698,
      "venue_name": "WWK Arena",
      "city": "Augsburg",
      "capacity": 30662,
      "match": "FC Augsburg vs Borussia Mönchengladbach",
      "yellow_home": 2,
      "red_home": 0,
      "yellow_away": 4,
      "red_away": 0,
      "yellow_total": 6,
      "red_total": 0,
      "cards_total": 6
    },
    {
      "fixture_id": 1224020,
      "date": "2024-10-05T13:30:00+00:00",
      "venue_id": 699,
      "venue_name": "BayArena",
      "city": "Leverkusen",
      "capacity": 30210,
      "match": "Bayer Leverkusen vs Holstein Kiel",
      "yellow_home": 2,
      "red_home": 0,
      "yellow_away": 2,
      "red_away": 0,
      "yellow_total": 4,
      "red_total": 0,
      "cards_total": 4
    },
    {
      "fixture_id": 1224027,
      "date": "2024-10-05T13:30:00+00:00",
      "venue_id": 751,
      "venue_name": "Vonovia Ruhrstadion",
      "city": "Bochum",
      "capacity": 27599,
      "match": "VfL Bochum vs VfL Wolfsburg",
      "yellow_home": 1,
      "red_home": 0,
      "yellow_away": 2,
      "red_away": 0,
      "yellow_total": 3,
      "red_total": 0,
      "cards_total": 3
    },
    {
      "fixture_id": 1224026,
      "date": "2024-10-05T13:30:00+00:00",
      "venue_id": 748,
      "venue_name": "Stadion An der Alten Försterei",
      "city": "Berlin",
      "capacity": 22467,
      "match": "Union Berlin vs Borussia Dortmund",
      "yellow_home": 4,
      "red_home": 0,
      "yellow_away": 4,
      "red_away": 0,
      "yellow_total": 8,
      "red_total": 0,
      "cards_total": 8
    },
    {
      "fixture_id": 1224028,
      "date": "2024-10-05T16:30:00+00:00",
      "venue_id": 745,
      "venue_name": "Millerntor-Stadion",
      "city": "Hamburg",
      "capacity": 29564,
      "match": "FC St. Pauli vs FSV Mainz 05",
      "yellow_home": 0,
      "red_home": 0,
      "yellow_away": 3,
      "red_away": 0,
      "yellow_total": 3,
      "red_total": 0,
      "cards_total": 3
    },
    {
      "fixture_id": 1224023,
      "date": "2024-10-06T13:30:00+00:00",
      "venue_id": 723,
      "venue_name": "Voith-Arena",
      "city": "Heidenheim an der Brenz",
      "capacity": 15000,
      "match": "1. FC Heidenheim vs RB Leipzig",
      "yellow_home": 2,
      "red_home": 0,
      "yellow_away": 2,
      "red_away": 0,
      "yellow_total": 4,
      "red_total": 0,
      "cards_total": 4
    },
    {
      "fixture_id": 1224033,
      "date": "2024-10-19T13:30:00+00:00",
      "venue_id": 12717,
      "venue_name": "Europa-Park Stadion",
      "city": "Freiburg im Breisgau",
      "capacity": 34700,
      "match": "SC Freiburg vs FC Augsburg",
      "yellow_home": 1,
      "red_home": 0,
      "yellow_away": 1,
      "red_away": 0,
      "yellow_total": 2,
      "red_total": 0,
      "cards_total": 2
    },
    {
      "fixture_id": 1224036,
      "date": "2024-10-19T13:30:00+00:00",
      "venue_id": 20471,
      "venue_name": "BORUSSIA-PARK",
      "city": "Mönchengladbach",
      "capacity": 54057,
      "match": "Borussia Mönchengladbach vs 1. FC Heidenheim",
      "yellow_home": 3,
      "red_home": 0,
      "yellow_away": 3,
      "red_away": 0,
      "yellow_total": 6,
      "red_total": 0,
      "cards_total": 6
    },
    {
      "fixture_id": 1224035,
      "date": "2024-10-19T13:30:00+00:00",
      "venue_id": 11899,
      "venue_name": "MEWA ARENA",
      "city": "Mainz",
      "capacity": 34034,
      "match": "FSV Mainz 05 vs RB Leipzig",
      "yellow_home": 1,
      "red_home": 0,
      "yellow_away": 3,
      "red_away": 0,
      "yellow_total": 4,
      "red_total": 0,
      "cards_total": 4
    },
    {
      "fixture_id": 1224032,
      "date": "2024-10-19T13:30:00+00:00",
      "venue_id": 724,
      "venue_name": "PreZero Arena",
      "city": "Sinsheim",
      "capacity": 30164,
      "match": "1899 Hoffenheim vs VfL Bochum",
      "yellow_home": 1,
      "red_home": 0,
      "yellow_away": 1,
      "red_away": 0,
      "yellow_total": 2,
      "red_total": 0,
      "cards_total": 2
    },
    {
      "fixture_id": 1224029,
      "date": "2024-10-19T13:30:00+00:00",
      "venue_id": 699,
      "venue_name": "BayArena",
      "city": "Leverkusen",
      "capacity": 30210,
      "match": "Bayer Leverkusen vs Eintracht Frankfurt",
      "yellow_home": 2,
      "red_home": 0,
      "yellow_away": 1,
      "red_away": 0,
      "yellow_total": 3,
      "red_total": 0,
      "cards_total": 3
    },
    {
      "fixture_id": 1224037,
      "date": "2024-10-20T13:30:00+00:00",
      "venue_id": 725,
      "venue_name": "Holstein-Stadion",
      "city": "Kiel",
      "capacity": 15034,
      "match": "Holstein Kiel vs Union Berlin",
      "yellow_home": 2,
      "red_home": 0,
      "yellow_away": 1,
      "red_away": 0,
      "yellow_total": 3,
      "red_total": 0,
      "cards_total": 3
    },
    {
      "fixture_id": 1224034,
      "date": "2024-10-20T15:30:00+00:00",
      "venue_id": 752,
      "venue_name": "Volkswagen Arena",
      "city": "Wolfsburg",
      "capacity": 30000,
      "match": "VfL Wolfsburg vs Werder Bremen",
      "yellow_home": 1,
      "red_home": 1,
      "yellow_away": 1,
      "red_away": 0,
      "yellow_total": 2,
      "red_total": 1,
      "cards_total": 3
    },
    {
      "fixture_id": 1224043,
      "date": "2024-10-25T18:30:00+00:00",
      "venue_id": 11899,
      "venue_name": "MEWA ARENA",
      "city": "Mainz",
      "capacity": 34034,
      "match": "FSV Mainz 05 vs Borussia Mönchengladbach",
      "yellow_home": 3,
      "red_home": 0,
      "yellow_away": 2,
      "red_away": 0,
      "yellow_total": 5,
      "red_total": 0,
      "cards_total": 5
    },
    {
      "fixture_id": 1224042,
      "date": "2024-10-26T13:30:00+00:00",
      "venue_id": 698,
      "venue_name": "WWK Arena",
      "city": "Augsburg",
      "capacity": 30662,
      "match": "FC Augsburg vs Borussia Dortmund",
      "yellow_home": 3,
      "red_home": 0,
      "yellow_away": 3,
      "red_away": 1,
      "yellow_total": 6,
      "red_total": 1,
      "cards_total": 7
    },
    {
      "fixture_id": 1224046,
      "date": "2024-10-26T13:30:00+00:00",
      "venue_id": 745,
      "venue_name": "Millerntor-Stadion",
      "city": "Hamburg",
      "capacity": 29564,
      "match": "FC St. Pauli vs VfL Wolfsburg",
      "yellow_home": 0,
      "red_home": 0,
      "yellow_away": 3,
      "red_away": 0,
      "yellow_total": 3,
      "red_total": 0,
      "cards_total": 3
    },
    {
      "fixture_id": 1224045,
      "date": "2024-10-27T14:30:00+00:00",
      "venue_id": 751,
      "venue_name": "Vonovia Ruhrstadion",
      "city": "Bochum",
      "capacity": 27599,
      "match": "VfL Bochum vs Bayern München",
      "yellow_home": 1,
      "red_home": 0,
      "yellow_away": 1,
      "red_away": 0,
      "yellow_total": 2,
      "red_total": 0,
      "cards_total": 2
    },
    {
      "fixture_id": 1224044,
      "date": "2024-10-27T16:30:00+00:00",
      "venue_id": 748,
      "venue_name": "Stadion An der Alten Försterei",
      "city": "Berlin",
      "capacity": 22467,
      "match": "Union Berlin vs Eintracht Frankfurt",
      "yellow_home": 5,
      "red_home": 0,
      "yellow_away": 3,
      "red_away": 1,
      "yellow_total": 8,
      "red_total": 1,
      "cards_total": 9
    },
    {
      "fixture_id": 1224040,
      "date": "2024-10-27T18:30:00+00:00",
      "venue_id": 723,
      "venue_name": "Voith-Arena",
      "city": "Heidenheim an der Brenz",
      "capacity": 15000,
      "match": "1. FC Heidenheim vs 1899 Hoffenheim",
      "yellow_home": 1,
      "red_home": 0,
      "yellow_away": 2,
      "red_away": 0,
      "yellow_total": 3,
      "red_total": 0,
      "cards_total": 3
    },
    {
      "fixture_id": 1224047,
      "date": "2024-11-01T19:30:00+00:00",
      "venue_id": 699,
      "venue_name": "BayArena",
      "city": "Leverkusen",
      "capacity": 30210,
      "match": "Bayer Leverkusen vs VfB Stuttgart",
      "yellow_home": 3,
      "red_home": 0,
      "yellow_away": 4,
      "red_away": 0,
      "yellow_total": 7,
      "red_total": 0,
      "cards_total": 7
    },
    {
      "fixture_id": 1224053,
      "date": "2024-11-02T14:30:00+00:00",
      "venue_id": 752,
      "venue_name": "Volkswagen Arena",
      "city": "Wolfsburg",
      "capacity": 30000,
      "match": "VfL Wolfsburg vs FC Augsburg",
      "yellow_home": 1,
      "red_home": 0,
      "yellow_away": 3,
      "red_away": 0,
      "yellow_total": 4,
      "red_total": 0,
      "cards_total": 4
    },
    {
      "fixture_id": 1224051,
      "date": "2024-11-02T14:30:00+00:00",
      "venue_id": 724,
      "venue_name": "PreZero Arena",
      "city": "Sinsheim",
      "capacity": 30164,
      "match": "1899 Hoffenheim vs FC St. Pauli",
      "yellow_home": 0,
      "red_home": 0,
      "yellow_away": 1,
      "red_away": 0,
      "yellow_total": 1,
      "red_total": 0,
      "cards_total": 1
    },
    {
      "fixture_id": 1224055,
      "date": "2024-11-02T14:30:00+00:00",
      "venue_id": 725,
      "venue_name": "Holstein-Stadion",
      "city": "Kiel",
      "capacity": 15034,
      "match": "Holstein Kiel vs 1. FC Heidenheim",
      "yellow_home": 4,
      "red_home": 0,
      "yellow_away": 5,
      "red_away": 0,
      "yellow_total": 9,
      "red_total": 0,
      "cards_total": 9
    },
    {
      "fixture_id": 1224052,
      "date": "2024-11-03T14:30:00+00:00",
      "venue_id": 12717,
      "venue_name": "Europa-Park Stadion",
      "city": "Freiburg im Breisgau",
      "capacity": 34700,
      "match": "SC Freiburg vs FSV Mainz 05",
      "yellow_home": 1,
      "red_home": 0,
      "yellow_away": 2,
      "red_away": 0,
      "yellow_total": 3,
      "red_total": 0,
      "cards_total": 3
    },
    {
      "fixture_id": 1224054,
      "date": "2024-11-03T16:30:00+00:00",
      "venue_id": 20471,
      "venue_name": "BORUSSIA-PARK",
      "city": "Mönchengladbach",
      "capacity": 54057,
      "match": "Borussia Mönchengladbach vs Werder Bremen",
      "yellow_home": 1,
      "red_home": 0,
      "yellow_away": 4,
      "red_away": 1,
      "yellow_total": 5,
      "red_total": 1,
      "cards_total": 6
    },
    {
      "fixture_id": 1224062,
      "date": "2024-11-08T19:30:00+00:00",
      "venue_id": 748,
      "venue_name": "Stadion An der Alten Försterei",
      "city": "Berlin",
      "capacity": 22467,
      "match": "Union Berlin vs SC Freiburg",
      "yellow_home": 2,
      "red_home": 0,
      "yellow_away": 0,
      "red_away": 0,
      "yellow_total": 2,
      "red_total": 0,
      "cards_total": 2
    },
    {
      "fixture_id": 1224061,
      "date": "2024-11-09T14:30:00+00:00",
      "venue_id": 11899,
      "venue_name": "MEWA ARENA",
      "city": "Mainz",
      "capacity": 34034,
      "match": "FSV Mainz 05 vs Borussia Dortmund",
      "yellow_home": 3,
      "red_home": 0,
      "yellow_away": 1,
      "red_away": 1,
      "yellow_total": 4,
      "red_total": 1,
      "cards_total": 5
    },
    {
      "fixture_id": 1224063,
      "date": "2024-11-09T14:30:00+00:00",
      "venue_id": 751,
      "venue_name": "Vonovia Ruhrstadion",
      "city": "Bochum",
      "capacity": 27599,
      "match": "VfL Bochum vs Bayer Leverkusen",
      "yellow_home": 0,
      "red_home": 0,
      "yellow_away": 1,
      "red_away": 0,
      "yellow_total": 1,
      "red_total": 0,
      "cards_total": 1
    },
    {
      "fixture_id": 1224064,
      "date": "2024-11-09T14:30:00+00:00",
      "venue_id": 745,
      "venue_name": "Millerntor-Stadion",
      "city": "Hamburg",
      "capacity": 29564,
      "match": "FC St. Pauli vs Bayern München",
      "yellow_home": 2,
      "red_home": 0,
      "yellow_away": 2,
      "red_away": 0,
      "yellow_total": 4,
      "red_total": 0,
      "cards_total": 4
    },
    {
      "fixture_id": 1224060,
      "date": "2024-11-10T14:30:00+00:00",
      "venue_id": 698,
      "venue_name": "WWK Arena",
      "city": "Augsburg",
      "capacity": 30662,
      "match": "FC Augsburg vs 1899 Hoffenheim",
      "yellow_home": 2,
      "red_home": 0,
      "yellow_away": 3,
      "red_away": 0,
      "yellow_total": 5,
      "red_total": 0,
      "cards_total": 5
    },
    {
      "fixture_id": 1224058,
      "date": "2024-11-10T18:30:00+00:00",
      "venue_id": 723,
      "venue_name": "Voith-Arena",
      "city": "Heidenheim an der Brenz",
      "capacity": 15000,
      "match": "1. FC Heidenheim vs VfL Wolfsburg",
      "yellow_home": 1,
      "red_home": 0,
      "yellow_away": 6,
      "red_away": 0,
      "yellow_total": 7,
      "red_total": 0,
      "cards_total": 7
    }
  ]
}